mobio/profiling/functions/__init__.py
mobio/profiling/functions/client.thrift
profiling_functions-1.1.6.dist-info/METADATA
profiling_functions-1.1.6.dist-info/WHEEL
profiling_functions-1.1.6.dist-info/top_level.txt
profiling_functions-1.1.6.dist-info/RECORD
